{"_ts":[1543641580,1543685798],"_r":{"breakdown":{"html":{"bytes":[6193,6194],"requests":[12,12]},"js":{"bytes":[552455,552454],"requests":[15,15]},"css":{"bytes":[69343,69343],"requests":[4,4]},"image":{"bytes":[5141026,5123505],"requests":[190,191]},"flash":{"bytes":[0,0],"requests":[0,0]},"font":{"bytes":[158641,158641],"requests":[6,6]},"video":{"bytes":[0,0],"requests":[0,0]},"other":{"bytes":[595062,627995],"requests":[5,5]}},"date":[1543641580,1543685798],"domElements":[2709,2679],"domInteractive":[1534,1501],"firstPaint":[451.9,423.0000000025],"fullyLoaded":[3422,3297],"id":["181201_8Y_1e18aac2644a622b8e057a21550a0bb2","181201_XJ_9c75217141e436883c74c93e04598594"],"loadTime":[3263,1816],"render":[1900,1900],"SpeedIndex":[2005,2002],"TTFB":[322,295],"videoFrames":[[{"_i":"ms_000000.jpg","_t":0,"_vc":0},{"_i":"ms_001900.jpg","_t":1900,"_vc":79},{"_i":"ms_002000.jpg","_t":2000,"_vc":79},{"_i":"ms_002100.jpg","_t":2100,"_vc":79},{"_i":"ms_002200.jpg","_t":2200,"_vc":79},{"_i":"ms_002300.jpg","_t":2300,"_vc":88},{"_i":"ms_002400.jpg","_t":2400,"_vc":91},{"_i":"ms_002500.jpg","_t":2500,"_vc":100}],[{"_i":"ms_000000.jpg","_t":0,"_vc":0},{"_i":"ms_001900.jpg","_t":1900,"_vc":79},{"_i":"ms_002000.jpg","_t":2000,"_vc":79},{"_i":"ms_002100.jpg","_t":2100,"_vc":79},{"_i":"ms_002200.jpg","_t":2200,"_vc":79},{"_i":"ms_002300.jpg","_t":2300,"_vc":88},{"_i":"ms_002400.jpg","_t":2400,"_vc":94},{"_i":"ms_002500.jpg","_t":2500,"_vc":100}]],"visualComplete":[2500,2500],"lighthouse":[15,15],"pagespeed":[12,12]}}