{"_ts":[1488327599],"_r":{"breakdown":{"html":{"bytes":[87154],"requests":[31]},"js":{"bytes":[389535],"requests":[39]},"css":{"bytes":[58309],"requests":[6]},"image":{"bytes":[2674381],"requests":[110]},"flash":{"bytes":[0],"requests":[0]},"font":{"bytes":[317060],"requests":[5]},"other":{"bytes":[2587],"requests":[3]}},"date":[1488327599],"domElements":[2048],"domInteractive":[6493],"firstPaint":[1614],"fullyLoaded":[18902],"id":["170301_AN_RE"],"loadTime":[10312],"render":[3385],"SpeedIndex":[3573],"TTFB":[127],"videoFrames":[[{"_t":0,"_vc":0},{"_t":3400,"_vc":59},{"_t":3800,"_vc":98},{"_t":5800,"_vc":99},{"_t":9400,"_vc":100}]],"visualComplete":[9375]}}