{"_ts":[1483262404,1483306473,1483350393],"_r":{"breakdown":{"html":{"bytes":[25058,25035,25177],"requests":[30,30,30]},"js":{"bytes":[692326,692317,692313],"requests":[23,23,23]},"css":{"bytes":[67538,67536,67537],"requests":[2,2,2]},"image":{"bytes":[11925931,9243915,9825756],"requests":[264,254,258]},"flash":{"bytes":[0,0,0],"requests":[0,0,0]},"font":{"bytes":[86199,86198,86200],"requests":[5,5,5]},"other":{"bytes":[605736,577655,522493],"requests":[3,3,3]}},"date":[1483262404,1483306473,1483350393],"domElements":[3206,3206,3206],"domInteractive":[4027,3977,4128],"firstPaint":[4324,4041,4345],"fullyLoaded":[22384,21040,22025],"id":["170101_7W_ADE","170101_Q9_RF8","170102_F1_DF3"],"loadTime":[17194,15183,16963],"render":[683,584,485],"SpeedIndex":[3095,2947,2450],"TTFB":[143,115,124],"videoFrames":[[{"_t":0,"_vc":0},{"_t":700,"_vc":80},{"_t":4900,"_vc":80},{"_t":5800,"_vc":80},{"_t":5900,"_vc":81},{"_t":6100,"_vc":80},{"_t":6200,"_vc":80},{"_t":6400,"_vc":81},{"_t":6700,"_vc":81},{"_t":6800,"_vc":80},{"_t":7000,"_vc":80},{"_t":7100,"_vc":81},{"_t":7300,"_vc":81},{"_t":7500,"_vc":80},{"_t":7600,"_vc":80},{"_t":7700,"_vc":81},{"_t":7900,"_vc":80},{"_t":8100,"_vc":80},{"_t":8300,"_vc":81},{"_t":8600,"_vc":81},{"_t":8900,"_vc":80},{"_t":9100,"_vc":80},{"_t":9500,"_vc":80},{"_t":9900,"_vc":80},{"_t":11500,"_vc":80},{"_t":12100,"_vc":88},{"_t":14000,"_vc":98},{"_t":14200,"_vc":100}],[{"_t":0,"_vc":0},{"_t":600,"_vc":80},{"_t":4400,"_vc":81},{"_t":4500,"_vc":81},{"_t":4700,"_vc":81},{"_t":4800,"_vc":81},{"_t":5000,"_vc":81},{"_t":5200,"_vc":81},{"_t":5400,"_vc":81},{"_t":8300,"_vc":81},{"_t":8600,"_vc":81},{"_t":9000,"_vc":81},{"_t":9500,"_vc":81},{"_t":10600,"_vc":81},{"_t":11700,"_vc":81},{"_t":13100,"_vc":88},{"_t":13300,"_vc":100}],[{"_t":0,"_vc":0},{"_t":500,"_vc":80},{"_t":4900,"_vc":81},{"_t":5300,"_vc":80},{"_t":5400,"_vc":80},{"_t":5600,"_vc":81},{"_t":5700,"_vc":81},{"_t":5900,"_vc":81},{"_t":6000,"_vc":81},{"_t":6200,"_vc":81},{"_t":6300,"_vc":81},{"_t":6600,"_vc":81},{"_t":6800,"_vc":81},{"_t":7000,"_vc":81},{"_t":7100,"_vc":81},{"_t":7200,"_vc":81},{"_t":7400,"_vc":81},{"_t":7600,"_vc":81},{"_t":7800,"_vc":81},{"_t":8700,"_vc":89},{"_t":12100,"_vc":93},{"_t":12600,"_vc":100}]],"visualComplete":[14188,13288,12582]}}